INSTALL.txt
LICENSE.txt
README.txt
development.ini
setup.cfg
setup.py
ISPManCCP.egg-info/PKG-INFO
ISPManCCP.egg-info/SOURCES.txt
ISPManCCP.egg-info/dependency_links.txt
ISPManCCP.egg-info/entry_points.txt
ISPManCCP.egg-info/not-zip-safe
ISPManCCP.egg-info/paste_deploy_config.ini_tmpl
ISPManCCP.egg-info/paster_plugins.txt
ISPManCCP.egg-info/requires.txt
ISPManCCP.egg-info/top_level.txt
extra-packages/pyperl-1.0.1d/Changes
extra-packages/pyperl-1.0.1d/MANIFEST
extra-packages/pyperl-1.0.1d/README
extra-packages/pyperl-1.0.1d/TODO
extra-packages/pyperl-1.0.1d/dbi-test.py
extra-packages/pyperl-1.0.1d/dbi.py
extra-packages/pyperl-1.0.1d/dbi2.py
extra-packages/pyperl-1.0.1d/dlhack.c
extra-packages/pyperl-1.0.1d/lang_lock.c
extra-packages/pyperl-1.0.1d/lang_lock.h
extra-packages/pyperl-1.0.1d/lang_map.c
extra-packages/pyperl-1.0.1d/lang_map.h
extra-packages/pyperl-1.0.1d/opcode.c
extra-packages/pyperl-1.0.1d/opts.pl
extra-packages/pyperl-1.0.1d/perlmod.py
extra-packages/pyperl-1.0.1d/perlmodule.c
extra-packages/pyperl-1.0.1d/perlmodule.h
extra-packages/pyperl-1.0.1d/perlmodule.pod
extra-packages/pyperl-1.0.1d/perlpickle.py
extra-packages/pyperl-1.0.1d/perlsh.py
extra-packages/pyperl-1.0.1d/pyo.c
extra-packages/pyperl-1.0.1d/pyo.h
extra-packages/pyperl-1.0.1d/setup.py
extra-packages/pyperl-1.0.1d/svrv_object.c
extra-packages/pyperl-1.0.1d/svrv_object.h
extra-packages/pyperl-1.0.1d/test.py
extra-packages/pyperl-1.0.1d/thrd_ctx.c
extra-packages/pyperl-1.0.1d/thrd_ctx.h
extra-packages/pyperl-1.0.1d/try_perlapi.pl
extra-packages/pyperl-1.0.1d/Python-Object/MANIFEST
extra-packages/pyperl-1.0.1d/Python-Object/Makefile.PL
extra-packages/pyperl-1.0.1d/Python-Object/Object.pm
extra-packages/pyperl-1.0.1d/Python-Object/Object.xs
extra-packages/pyperl-1.0.1d/Python-Object/PerlPyErr.h
extra-packages/pyperl-1.0.1d/Python-Object/pyinc.py
extra-packages/pyperl-1.0.1d/Python-Object/typemap
extra-packages/pyperl-1.0.1d/Python-Object/lib/Python.pm
extra-packages/pyperl-1.0.1d/Python-Object/lib/Python/Err.pm
extra-packages/pyperl-1.0.1d/patches/README
extra-packages/pyperl-1.0.1d/patches/perl-eval-leak
extra-packages/pyperl-1.0.1d/patches/perl-method-G_EVAL
extra-packages/pyperl-1.0.1d/patches/perl-nexttoke
extra-packages/pyperl-1.0.1d/patches/perl-vcroak-null
