Metadata-Version: 1.0
Name: ISPManCCP
Version: 0.0.1alpha3.1
Summary: Customer Control Panel for ISPMan
Home-page: http://ccp.ufsoft.org/
Author: Pedro Algarvio
Author-email: ufs@ufsoft.org
License: BSD
Keywords: ISPMan PyPerl Python Customer Control Pannel
Platform: Anywhere you've got ISPMan working.
Classifier: Development Status :: 3 - Alpha
Classifier: Environment :: Web Environment
Classifier: Intended Audience :: Customer Service
Classifier: License :: OSI Approved :: BSD License
Classifier: Natural Language :: English
Classifier: Natural Language :: Portuguese
Classifier: Programming Language :: Python
Classifier: Programming Language :: Perl
Classifier: Topic :: Database :: Front-Ends
Classifier: Topic :: Internet :: WWW/HTTP :: WSGI :: Application
Classifier: Topic :: Utilities
